{
  "team": {
    "id": "2579",
    "uid": "s:40~l:41~t:2579",
    "slug": "south-carolina-gamecocks",
    "location": "South Carolina",
    "name": "Gamecocks",
    "nickname": "South Carolina",
    "abbreviation": "SC",
    "displayName": "South Carolina Gamecocks",
    "shortDisplayName": "South Carolina",
    "color": "73000a",
    "alternateColor": "000000",
    "isActive": true,
    "logos": [
      {
        "href": "https://a.espncdn.com/i/teamlogos/ncaa/500/2579.png",
        "width": 500,
        "height": 500,
        "alt": "",
        "rel": [
          "full",
          "default"
        ],
        "lastUpdated": "2025-12-19T23:48Z"
      },
      {
        "href": "https://a.espncdn.com/i/teamlogos/ncaa/500-dark/2579.png",
        "width": 500,
        "height": 500,
        "alt": "",
        "rel": [
          "full",
          "dark"
        ],
        "lastUpdated": "2025-12-19T23:47Z"
      },
      {
        "href": "https://a.espncdn.com/guid/5634bc86-a75d-4d13-10c9-efd935c5a158/logos/primary_logo_on_white_color.png",
        "width": 4096,
        "height": 4096,
        "alt": "",
        "rel": [
          "full",
          "primary_logo_on_white_color"
        ],
        "lastUpdated": "2024-11-11T01:36Z"
      },
      {
        "href": "https://a.espncdn.com/guid/5634bc86-a75d-4d13-10c9-efd935c5a158/logos/primary_logo_on_black_color.png",
        "width": 4096,
        "height": 4096,
        "alt": "",
        "rel": [
          "full",
          "primary_logo_on_black_color"
        ],
        "lastUpdated": "2024-11-11T01:36Z"
      },
      {
        "href": "https://a.espncdn.com/guid/5634bc86-a75d-4d13-10c9-efd935c5a158/logos/primary_logo_on_primary_color.png",
        "width": 4096,
        "height": 4096,
        "alt": "",
        "rel": [
          "full",
          "primary_logo_on_primary_color"
        ],
        "lastUpdated": "2025-12-24T15:04Z"
      },
      {
        "href": "https://a.espncdn.com/guid/5634bc86-a75d-4d13-10c9-efd935c5a158/logos/primary_logo_on_secondary_color.png",
        "width": 4096,
        "height": 4096,
        "alt": "",
        "rel": [
          "full",
          "primary_logo_on_secondary_color"
        ],
        "lastUpdated": "2025-12-24T15:04Z"
      },
      {
        "href": "https://a.espncdn.com/guid/5634bc86-a75d-4d13-10c9-efd935c5a158/logos/secondary_logo_on_white_color.png",
        "width": 4096,
        "height": 4096,
        "alt": "",
        "rel": [
          "full",
          "secondary_logo_on_white_color"
        ],
        "lastUpdated": "2024-11-11T01:36Z"
      },
      {
        "href": "https://a.espncdn.com/guid/5634bc86-a75d-4d13-10c9-efd935c5a158/logos/secondary_logo_on_black_color.png",
        "width": 4096,
        "height": 4096,
        "alt": "",
        "rel": [
          "full",
          "secondary_logo_on_black_color"
        ],
        "lastUpdated": "2024-11-11T01:36Z"
      },
      {
        "href": "https://a.espncdn.com/guid/5634bc86-a75d-4d13-10c9-efd935c5a158/logos/secondary_logo_on_primary_color.png",
        "width": 4096,
        "height": 4096,
        "alt": "",
        "rel": [
          "full",
          "secondary_logo_on_primary_color"
        ],
        "lastUpdated": "2024-11-11T01:36Z"
      },
      {
        "href": "https://a.espncdn.com/guid/5634bc86-a75d-4d13-10c9-efd935c5a158/logos/secondary_logo_on_secondary_color.png",
        "width": 4096,
        "height": 4096,
        "alt": "",
        "rel": [
          "full",
          "secondary_logo_on_secondary_color"
        ],
        "lastUpdated": "2024-11-11T01:36Z"
      }
    ],
    "record": {
      "items": [
        {
          "description": "Overall Record",
          "type": "total",
          "summary": "11-10",
          "stats": [
            {
              "name": "OTLosses",
              "value": 1.0
            },
            {
              "name": "OTWins",
              "value": 1.0
            },
            {
              "name": "avgPointsAgainst",
              "value": 74.04762
            },
            {
              "name": "avgPointsFor",
              "value": 76.90476
            },
            {
              "name": "differential",
              "value": 2.9000000000000057
            },
            {
              "name": "divisionWinPercent",
              "value": 0.0
            },
            {
              "name": "gamesBehind",
              "value": 7.0
            },
            {
              "name": "gamesPlayed",
              "value": 21.0
            },
            {
              "name": "leagueWinPercent",
              "value": 0.25
            },
            {
              "name": "losses",
              "value": 10.0
            },
            {
              "name": "playoffSeed",
              "value": 14.0
            },
            {
              "name": "pointDifferential",
              "value": 60.0
            },
            {
              "name": "points",
              "value": 0.5
            },
            {
              "name": "pointsAgainst",
              "value": 1555.0
            },
            {
              "name": "pointsFor",
              "value": 1615.0
            },
            {
              "name": "streak",
              "value": -2.0
            },
            {
              "name": "ties",
              "value": 0.0
            },
            {
              "name": "winPercent",
              "value": 0.52380955
            },
            {
              "name": "wins",
              "value": 11.0
            }
          ]
        },
        {
          "description": "Home Record",
          "type": "home",
          "summary": "10-4",
          "stats": [
            {
              "name": "OTLosses",
              "value": 0.0
            },
            {
              "name": "OTWins",
              "value": 0.0
            },
            {
              "name": "avgPointsAgainst",
              "value": 70.71429
            },
            {
              "name": "avgPointsFor",
              "value": 79.78571
            },
            {
              "name": "differential",
              "value": 9.099999999999994
            },
            {
              "name": "divisionWinPercent",
              "value": 0.0
            },
            {
              "name": "gamesBehind",
              "value": 3.5
            },
            {
              "name": "gamesPlayed",
              "value": 14.0
            },
            {
              "name": "leagueWinPercent",
              "value": 0.25
            },
            {
              "name": "losses",
              "value": 4.0
            },
            {
              "name": "playoffSeed",
              "value": 14.0
            },
            {
              "name": "pointDifferential",
              "value": 127.0
            },
            {
              "name": "points",
              "value": 3.0
            },
            {
              "name": "pointsAgainst",
              "value": 990.0
            },
            {
              "name": "pointsFor",
              "value": 1117.0
            },
            {
              "name": "streak",
              "value": -2.0
            },
            {
              "name": "ties",
              "value": 0.0
            },
            {
              "name": "winPercent",
              "value": 0.71428573
            },
            {
              "name": "wins",
              "value": 10.0
            }
          ]
        },
        {
          "description": "Away Record",
          "type": "road",
          "summary": "1-4",
          "stats": [
            {
              "name": "OTLosses",
              "value": 0.0
            },
            {
              "name": "OTWins",
              "value": 0.0
            },
            {
              "name": "avgPointsAgainst",
              "value": 81.4
            },
            {
              "name": "avgPointsFor",
              "value": 69.8
            },
            {
              "name": "differential",
              "value": -11.600000000000009
            },
            {
              "name": "divisionWinPercent",
              "value": 0.0
            },
            {
              "name": "gamesBehind",
              "value": 2.5
            },
            {
              "name": "gamesPlayed",
              "value": 5.0
            },
            {
              "name": "leagueWinPercent",
              "value": 0.25
            },
            {
              "name": "losses",
              "value": 4.0
            },
            {
              "name": "playoffSeed",
              "value": 14.0
            },
            {
              "name": "pointDifferential",
              "value": -58.0
            },
            {
              "name": "points",
              "value": -1.5
            },
            {
              "name": "pointsAgainst",
              "value": 407.0
            },
            {
              "name": "pointsFor",
              "value": 349.0
            },
            {
              "name": "streak",
              "value": -2.0
            },
            {
              "name": "ties",
              "value": 0.0
            },
            {
              "name": "winPercent",
              "value": 0.2
            },
            {
              "name": "wins",
              "value": 1.0
            }
          ]
        }
      ]
    },
    "groups": {
      "id": "23",
      "parent": {
        "id": "50"
      },
      "isConference": true
    },
    "links": [
      {
        "language": "en-US",
        "rel": [
          "clubhouse",
          "desktop",
          "team"
        ],
        "href": "https://www.espn.com/mens-college-basketball/team/_/id/2579/south-carolina-gamecocks",
        "text": "Clubhouse",
        "shortText": "Clubhouse",
        "isExternal": false,
        "isPremium": false
      },
      {
        "language": "en-US",
        "rel": [
          "roster",
          "desktop",
          "team"
        ],
        "href": "https://www.espn.com/mens-college-basketball/team/roster/_/id/2579",
        "text": "Roster",
        "shortText": "Roster",
        "isExternal": false,
        "isPremium": false
      },
      {
        "language": "en-US",
        "rel": [
          "stats",
          "desktop",
          "team"
        ],
        "href": "https://www.espn.com/mens-college-basketball/team/stats/_/id/2579",
        "text": "Statistics",
        "shortText": "Statistics",
        "isExternal": false,
        "isPremium": false
      },
      {
        "language": "en-US",
        "rel": [
          "schedule",
          "desktop",
          "team"
        ],
        "href": "https://www.espn.com/mens-college-basketball/team/schedule/_/id/2579",
        "text": "Schedule",
        "shortText": "Schedule",
        "isExternal": false,
        "isPremium": false
      },
      {
        "language": "en-US",
        "rel": [
          "photos",
          "desktop",
          "team"
        ],
        "href": "https://www.espn.com/mens-college-basketball/team/photos/_/id/2579",
        "text": "photos",
        "shortText": "photos",
        "isExternal": false,
        "isPremium": false
      },
      {
        "language": "en-US",
        "rel": [
          "tickets",
          "desktop",
          "team"
        ],
        "href": "https://www.vividseats.com/south-carolina-gamecocks-mens-basketball-tickets--sports-ncaa-basketball/performer/3313?wsUser=717",
        "text": "Tickets",
        "shortText": "Tickets",
        "isExternal": true,
        "isPremium": false
      }
    ],
    "nextEvent": [
      {
        "id": "401808212",
        "date": "2026-01-31T18:00Z",
        "name": "LSU Tigers at South Carolina Gamecocks",
        "shortName": "LSU @ SC",
        "season": {
          "year": 2026,
          "displayName": "2025-26"
        },
        "seasonType": {
          "id": "2",
          "type": 2,
          "name": "Regular Season",
          "abbreviation": "reg"
        },
        "week": {
          "number": 13,
          "text": "Week 13"
        },
        "timeValid": true,
        "competitions": [
          {
            "id": "401808212",
            "date": "2026-01-31T18:00Z",
            "attendance": 0,
            "type": {
              "id": "1",
              "text": "Standard",
              "abbreviation": "STD",
              "slug": "standard",
              "type": "standard"
            },
            "timeValid": true,
            "neutralSite": false,
            "boxscoreAvailable": false,
            "ticketsAvailable": true,
            "venue": {
              "fullName": "Colonial Life Arena",
              "address": {
                "city": "Columbia",
                "state": "SC"
              }
            },
            "competitors": [
              {
                "id": "2579",
                "type": "team",
                "order": 0,
                "homeAway": "home",
                "team": {
                  "id": "2579",
                  "location": "South Carolina",
                  "nickname": "South Carolina",
                  "abbreviation": "SC",
                  "displayName": "South Carolina Gamecocks",
                  "shortDisplayName": "South Carolina",
                  "logos": [
                    {
                      "href": "https://a.espncdn.com/i/teamlogos/ncaa/500/2579.png",
                      "width": 500,
                      "height": 500,
                      "alt": "",
                      "rel": [
                        "full",
                        "default"
                      ],
                      "lastUpdated": "2025-12-19T23:48Z"
                    },
                    {
                      "href": "https://a.espncdn.com/i/teamlogos/ncaa/500-dark/2579.png",
                      "width": 500,
                      "height": 500,
                      "alt": "",
                      "rel": [
                        "full",
                        "dark"
                      ],
                      "lastUpdated": "2025-12-19T23:47Z"
                    },
                    {
                      "href": "https://a.espncdn.com/guid/5634bc86-a75d-4d13-10c9-efd935c5a158/logos/primary_logo_on_white_color.png",
                      "width": 4096,
                      "height": 4096,
                      "alt": "",
                      "rel": [
                        "full",
                        "primary_logo_on_white_color"
                      ],
                      "lastUpdated": "2024-11-11T01:36Z"
                    },
                    {
                      "href": "https://a.espncdn.com/guid/5634bc86-a75d-4d13-10c9-efd935c5a158/logos/primary_logo_on_black_color.png",
                      "width": 4096,
                      "height": 4096,
                      "alt": "",
                      "rel": [
                        "full",
                        "primary_logo_on_black_color"
                      ],
                      "lastUpdated": "2024-11-11T01:36Z"
                    },
                    {
                      "href": "https://a.espncdn.com/guid/5634bc86-a75d-4d13-10c9-efd935c5a158/logos/primary_logo_on_primary_color.png",
                      "width": 4096,
                      "height": 4096,
                      "alt": "",
                      "rel": [
                        "full",
                        "primary_logo_on_primary_color"
                      ],
                      "lastUpdated": "2025-12-24T15:04Z"
                    },
                    {
                      "href": "https://a.espncdn.com/guid/5634bc86-a75d-4d13-10c9-efd935c5a158/logos/primary_logo_on_secondary_color.png",
                      "width": 4096,
                      "height": 4096,
                      "alt": "",
                      "rel": [
                        "full",
                        "primary_logo_on_secondary_color"
                      ],
                      "lastUpdated": "2025-12-24T15:04Z"
                    },
                    {
                      "href": "https://a.espncdn.com/guid/5634bc86-a75d-4d13-10c9-efd935c5a158/logos/secondary_logo_on_white_color.png",
                      "width": 4096,
                      "height": 4096,
                      "alt": "",
                      "rel": [
                        "full",
                        "secondary_logo_on_white_color"
                      ],
                      "lastUpdated": "2024-11-11T01:36Z"
                    },
                    {
                      "href": "https://a.espncdn.com/guid/5634bc86-a75d-4d13-10c9-efd935c5a158/logos/secondary_logo_on_black_color.png",
                      "width": 4096,
                      "height": 4096,
                      "alt": "",
                      "rel": [
                        "full",
                        "secondary_logo_on_black_color"
                      ],
                      "lastUpdated": "2024-11-11T01:36Z"
                    },
                    {
                      "href": "https://a.espncdn.com/guid/5634bc86-a75d-4d13-10c9-efd935c5a158/logos/secondary_logo_on_primary_color.png",
                      "width": 4096,
                      "height": 4096,
                      "alt": "",
                      "rel": [
                        "full",
                        "secondary_logo_on_primary_color"
                      ],
                      "lastUpdated": "2024-11-11T01:36Z"
                    },
                    {
                      "href": "https://a.espncdn.com/guid/5634bc86-a75d-4d13-10c9-efd935c5a158/logos/secondary_logo_on_secondary_color.png",
                      "width": 4096,
                      "height": 4096,
                      "alt": "",
                      "rel": [
                        "full",
                        "secondary_logo_on_secondary_color"
                      ],
                      "lastUpdated": "2024-11-11T01:36Z"
                    }
                  ],
                  "links": [
                    {
                      "rel": [
                        "clubhouse",
                        "desktop",
                        "team"
                      ],
                      "href": "https://www.espn.com/mens-college-basketball/team/_/id/2579/south-carolina-gamecocks",
                      "text": "Clubhouse"
                    },
                    {
                      "rel": [
                        "roster",
                        "desktop",
                        "team"
                      ],
                      "href": "https://www.espn.com/mens-college-basketball/team/roster/_/id/2579",
                      "text": "Roster"
                    },
                    {
                      "rel": [
                        "stats",
                        "desktop",
                        "team"
                      ],
                      "href": "https://www.espn.com/mens-college-basketball/team/stats/_/id/2579",
                      "text": "Statistics"
                    },
                    {
                      "rel": [
                        "schedule",
                        "desktop",
                        "team"
                      ],
                      "href": "https://www.espn.com/mens-college-basketball/team/schedule/_/id/2579",
                      "text": "Schedule"
                    },
                    {
                      "rel": [
                        "photos",
                        "desktop",
                        "team"
                      ],
                      "href": "https://www.espn.com/mens-college-basketball/team/photos/_/id/2579",
                      "text": "photos"
                    },
                    {
                      "rel": [
                        "tickets",
                        "desktop",
                        "team"
                      ],
                      "href": "https://www.vividseats.com/south-carolina-gamecocks-mens-basketball-tickets--sports-ncaa-basketball/performer/3313?wsUser=717",
                      "text": "Tickets"
                    }
                  ]
                },
                "curatedRank": {
                  "current": 99
                }
              },
              {
                "id": "99",
                "type": "team",
                "order": 1,
                "homeAway": "away",
                "team": {
                  "id": "99",
                  "location": "LSU",
                  "nickname": "LSU",
                  "abbreviation": "LSU",
                  "displayName": "LSU Tigers",
                  "shortDisplayName": "LSU",
                  "logos": [
                    {
                      "href": "https://a.espncdn.com/i/teamlogos/ncaa/500/99.png",
                      "width": 500,
                      "height": 500,
                      "alt": "",
                      "rel": [
                        "full",
                        "default"
                      ],
                      "lastUpdated": "2025-12-19T23:48Z"
                    },
                    {
                      "href": "https://a.espncdn.com/i/teamlogos/ncaa/500-dark/99.png",
                      "width": 500,
                      "height": 500,
                      "alt": "",
                      "rel": [
                        "full",
                        "dark"
                      ],
                      "lastUpdated": "2025-12-19T23:47Z"
                    },
                    {
                      "href": "https://a.espncdn.com/guid/0082bd85-3d3b-7d16-f176-b72443a93398/logos/primary_logo_on_white_color.png",
                      "width": 4096,
                      "height": 4096,
                      "alt": "",
                      "rel": [
                        "full",
                        "primary_logo_on_white_color"
                      ],
                      "lastUpdated": "2024-11-11T01:52Z"
                    },
                    {
                      "href": "https://a.espncdn.com/guid/0082bd85-3d3b-7d16-f176-b72443a93398/logos/primary_logo_on_black_color.png",
                      "width": 4096,
                      "height": 4096,
                      "alt": "",
                      "rel": [
                        "full",
                        "primary_logo_on_black_color"
                      ],
                      "lastUpdated": "2024-11-11T01:52Z"
                    },
                    {
                      "href": "https://a.espncdn.com/guid/0082bd85-3d3b-7d16-f176-b72443a93398/logos/primary_logo_on_primary_color.png",
                      "width": 4096,
                      "height": 4096,
                      "alt": "",
                      "rel": [
                        "full",
                        "primary_logo_on_primary_color"
                      ],
                      "lastUpdated": "2025-12-24T14:51Z"
                    },
                    {
                      "href": "https://a.espncdn.com/guid/0082bd85-3d3b-7d16-f176-b72443a93398/logos/primary_logo_on_secondary_color.png",
                      "width": 4096,
                      "height": 4096,
                      "alt": "",
                      "rel": [
                        "full",
                        "primary_logo_on_secondary_color"
                      ],
                      "lastUpdated": "2025-12-24T14:52Z"
                    },
                    {
                      "href": "https://a.espncdn.com/guid/0082bd85-3d3b-7d16-f176-b72443a93398/logos/secondary_logo_on_white_color.png",
                      "width": 4096,
                      "height": 4096,
                      "alt": "",
                      "rel": [
                        "full",
                        "secondary_logo_on_white_color"
                      ],
                      "lastUpdated": "2024-11-11T01:52Z"
                    },
                    {
                      "href": "https://a.espncdn.com/guid/0082bd85-3d3b-7d16-f176-b72443a93398/logos/secondary_logo_on_black_color.png",
                      "width": 4096,
                      "height": 4096,
                      "alt": "",
                      "rel": [
                        "full",
                        "secondary_logo_on_black_color"
                      ],
                      "lastUpdated": "2024-11-11T01:52Z"
                    },
                    {
                      "href": "https://a.espncdn.com/guid/0082bd85-3d3b-7d16-f176-b72443a93398/logos/secondary_logo_on_primary_color.png",
                      "width": 4096,
                      "height": 4096,
                      "alt": "",
                      "rel": [
                        "full",
                        "secondary_logo_on_primary_color"
                      ],
                      "lastUpdated": "2024-11-11T01:52Z"
                    },
                    {
                      "href": "https://a.espncdn.com/guid/0082bd85-3d3b-7d16-f176-b72443a93398/logos/secondary_logo_on_secondary_color.png",
                      "width": 4096,
                      "height": 4096,
                      "alt": "",
                      "rel": [
                        "full",
                        "secondary_logo_on_secondary_color"
                      ],
                      "lastUpdated": "2024-11-11T01:52Z"
                    }
                  ],
                  "links": [
                    {
                      "rel": [
                        "clubhouse",
                        "desktop",
                        "team"
                      ],
                      "href": "https://www.espn.com/mens-college-basketball/team/_/id/99/lsu-tigers",
                      "text": "Clubhouse"
                    },
                    {
                      "rel": [
                        "roster",
                        "desktop",
                        "team"
                      ],
                      "href": "https://www.espn.com/mens-college-basketball/team/roster/_/id/99",
                      "text": "Roster"
                    },
                    {
                      "rel": [
                        "stats",
                        "desktop",
                        "team"
                      ],
                      "href": "https://www.espn.com/mens-college-basketball/team/stats/_/id/99",
                      "text": "Statistics"
                    },
                    {
                      "rel": [
                        "schedule",
                        "desktop",
                        "team"
                      ],
                      "href": "https://www.espn.com/mens-college-basketball/team/schedule/_/id/99",
                      "text": "Schedule"
                    },
                    {
                      "rel": [
                        "photos",
                        "desktop",
                        "team"
                      ],
                      "href": "https://www.espn.com/mens-college-basketball/team/photos/_/id/99",
                      "text": "photos"
                    },
                    {
                      "rel": [
                        "tickets",
                        "desktop",
                        "team"
                      ],
                      "href": "https://www.vividseats.com/lsu-tigers-mens-basketball-tickets--sports-ncaa-basketball/performer/3227?wsUser=717",
                      "text": "Tickets"
                    }
                  ]
                },
                "curatedRank": {
                  "current": 99
                }
              }
            ],
            "notes": [],
            "broadcasts": [
              {
                "type": {
                  "id": "4",
                  "shortName": "Streaming"
                },
                "market": {
                  "id": "1",
                  "type": "National"
                },
                "media": {
                  "shortName": "SECN+",
                  "logo": "https://a.espncdn.com/guid/d1e3d7c4-8e72-37f3-b9b9-515573fd5526/logos/default.png",
                  "darkLogo": ""
                },
                "lang": "en",
                "region": "us",
                "partnered": false
              }
            ],
            "tickets": [
              {
                "id": "5828745",
                "summary": "Tickets as low as $5",
                "description": "LSU Tigers at South Carolina Gamecocks Mens Basketball",
                "maxPrice": 7366.94,
                "startingPrice": 5.73,
                "numberAvailable": 1005,
                "totalPostings": 235,
                "links": [
                  {
                    "rel": [
                      "tickets",
                      "desktop",
                      "event"
                    ],
                    "href": "https://www.vividseats.com/south-carolina-gamecocks-mens-basketball-tickets-colonial-life-arena-10-17-2025--sports-ncaa-basketball/production/5828745?wsUser=717"
                  },
                  {
                    "rel": [
                      "tickets",
                      "desktop",
                      "venue"
                    ],
                    "href": "https://www.vividseats.com/colonial-life-arena-tickets/venue/6158?wsUser=717"
                  }
                ]
              }
            ],
            "status": {
              "clock": 0.0,
              "displayClock": "0:00",
              "period": 0,
              "type": {
                "id": "1",
                "name": "STATUS_SCHEDULED",
                "state": "pre",
                "completed": false,
                "description": "Scheduled",
                "detail": "Sat, January 31st at 1:00 PM EST",
                "shortDetail": "1/31 - 1:00 PM EST"
              }
            }
          }
        ],
        "links": [
          {
            "language": "en-US",
            "rel": [
              "summary",
              "desktop",
              "event"
            ],
            "href": "https://www.espn.com/mens-college-basketball/game/_/gameId/401808212/lsu-south-carolina",
            "text": "Gamecast",
            "shortText": "Summary",
            "isExternal": false,
            "isPremium": false
          },
          {
            "language": "en-US",
            "rel": [
              "summary",
              "sportscenter",
              "app",
              "event"
            ],
            "href": "sportscenter://x-callback-url/showGame?sportName=basketball&leagueAbbrev=mens-college-basketball&gameId=401808212",
            "text": "Gamecast",
            "shortText": "Summary",
            "isExternal": false,
            "isPremium": false
          },
          {
            "language": "en-US",
            "rel": [
              "watchespn",
              "desktop",
              "event"
            ],
            "href": "https://www.espn.com/watchespn/index?gameId=401808212&sourceLang=en",
            "text": "WatchESPN",
            "shortText": "WatchESPN",
            "isExternal": false,
            "isPremium": false
          },
          {
            "language": "en-US",
            "rel": [
              "watchespn",
              "app",
              "event"
            ],
            "href": "watchespn://showEvent?gameId=401808212&sourceLang=en",
            "text": "WatchESPN",
            "shortText": "WatchESPN",
            "isExternal": false,
            "isPremium": false
          }
        ]
      }
    ],
    "standingSummary": "14th in SEC"
  }
}